README.md
setup.py
amazon_product_scraper_with_python/__init__.py
amazon_product_scraper_with_python.egg-info/PKG-INFO
amazon_product_scraper_with_python.egg-info/SOURCES.txt
amazon_product_scraper_with_python.egg-info/dependency_links.txt
amazon_product_scraper_with_python.egg-info/requires.txt
amazon_product_scraper_with_python.egg-info/top_level.txt