Metadata-Version: 2.1
Name: amazon-product-scraper-with-python
Version: 1.0.1
Summary: A python library to scrape product data on amazon automatically.
Home-page: https://amazon-api.datakund.com/en/latest/
Author: DataKund
Author-email: datakund@gmail.com
License: Apache License 2.0
Keywords: amazon python bot_studio scraper data product info web-scraping
Platform: UNKNOWN
